[
  {
    "author": "Chinua Achebe",
    "title": "Things Fall Apart"
  },
  {
    "author": "Hans Christian Andersen",
    "title": "Fairy tales"
  },
  {
    "author": "Dante Alighieri",
    "title": "The Divine Comedy"
  },
  {
    "title": "jhgfd",
    "author": "jhgf"
  },
  {
    "title": "Game of Thrones",
    "author": "George Martin"
  },
  {
    "title": "Lord of Rings",
    "author": "John Tolkien"
  },
  {
    "title": "Lord of Rings",
    "author": "JOhn Tolkien"
  },
  {
    "title": "Lord of Rings",
    "author": "JOhn Tolkien"
  },
  {
    "title": "Thirteen Months of Sunshine",
    "author": "Dagnachew Worku"
  },
  {
    "title": "Thirteen Months of Sunshine",
    "author": "Dagnachew Worku"
  },
  {
    "title": "Homo Sapiens",
    "author": "Noah Harari"
  },
  {
    "title": "Homo Sapiens",
    "author": "Noah Harari"
  },
  {
    "title": "Alchemist",
    "author": "Paulo Coleho"
  },
  {
    "title": "Alchemist",
    "author": "Paulo Coleho"
  }
]